{
    "alpha" : 0.5,
    "beta"  : 0.1,
    "lamb"  : 0.4,
    "mu" : 1.4,
    "INTRA" : 0.1,
    "LR_IMG" : 0.01,
    "LR_TXT" : 0.01,
    "MIN" : -0.52,
    "MAX" : 0.68,
    "ALPHA" : 2,
    "LOC_LEFT" : -0.49,
    "SCALE_LEFT" : 0.019,
    "BETA" : 4,
    "LOC_RIGHT" : -0.49,
    "SCALE_RIGHT" : 0.088,
    "L1" : 0.1,
    "L2" : 0.2,
    "LABEL_DIR" : "dataset/Flickr/mirflickr25k-lall.mat",
    "TXT_DIR" : "dataset/Flickr/mirflickr25k-yall.mat",
    "IMG_DIR" : "dataset/Flickr/mirflickr25k-iall.mat",

    "HASH_BIT" : 128,
    "BATCH_SIZE" : 32,
    "MOMENTUM" : 0.9,
    "WEIGHT_DECAY" : 5e-4,
    "GPU_ID" : 0,
    "NUM_WORKERS" : 8,
    "EPOCH_INTERVAL" : 2,
    "NUM_EPOCH" : 300,
    "EVAL_INTERVAL" : 40,
    "MODEL_DIR" : "./checkpoints",
    "CHECKPOINT" : "flikcr_128bit.pth"
}
